MANIFEST.in
README.md
setup.py
pyGPs/__init__.py
pyGPs.egg-info/PKG-INFO
pyGPs.egg-info/SOURCES.txt
pyGPs.egg-info/dependency_links.txt
pyGPs.egg-info/requires.txt
pyGPs.egg-info/top_level.txt
pyGPs/Core/__init__.py
pyGPs/Core/cov.py
pyGPs/Core/gp.py
pyGPs/Core/inf.py
pyGPs/Core/lik.py
pyGPs/Core/mean.py
pyGPs/Core/opt.py
pyGPs/Core/tools.py
pyGPs/Demo/__init__.py
pyGPs/Demo/generate_data_for_Rasmussen_examples.py
pyGPs/Demo/Airline/airlinedata.mat
pyGPs/Demo/Airline/demo_Airline.py
pyGPs/Demo/Classification/classification_data.npz
pyGPs/Demo/Classification/demo_GPC.py
pyGPs/Demo/Classification/demo_GPC_FITC.py
pyGPs/Demo/Clustering/__init__.py
pyGPs/Demo/Clustering/demo_clustering.py
pyGPs/Demo/Clustering/pyGP_extension.py
pyGPs/Demo/GraphData/demo_GraphKernel.py
pyGPs/Demo/GraphData/graphData/MUTAG.mat
pyGPs/Demo/GraphData/graphData/MUTAG.npz
pyGPs/Demo/GraphData/graphData/toNumpyMatrix.py
pyGPs/Demo/Housing/demo_Housing.py
pyGPs/Demo/Housing/housing.txt
pyGPs/Demo/Housing/housing_README.txt
pyGPs/Demo/JHUI/demo_Validation.py
pyGPs/Demo/JHUI/ionosphere.data.txt
pyGPs/Demo/JHUI/ionosphere.names.txt
pyGPs/Demo/JHUI/ionosphere_README.txt
pyGPs/Demo/MaunaLoa/demo_MaunaLoa.py
pyGPs/Demo/MaunaLoa/mauna.txt
pyGPs/Demo/MaunaLoa/mauna_README.txt
pyGPs/Demo/Regression/demo_GPR.py
pyGPs/Demo/Regression/demo_GPR_FITC.py
pyGPs/Demo/Regression/regression_data.npz
pyGPs/Demo/USPS/demo_GPMC.py
pyGPs/Demo/USPS/demo_NodeKernel.py
pyGPs/Demo/USPS/loadBinaryUSPS.m
pyGPs/Demo/USPS/loadBinaryUSPS.py
pyGPs/Demo/USPS/usps_README.txt
pyGPs/Demo/USPS/usps_all.mat
pyGPs/Demo/USPS/usps_resampled.mat
pyGPs/GraphExtensions/__init__.py
pyGPs/GraphExtensions/graphKernels.py
pyGPs/GraphExtensions/graphUtil.py
pyGPs/GraphExtensions/nodeKernels.py
pyGPs/Optimization/__init__.py
pyGPs/Optimization/conf.py
pyGPs/Optimization/minimize.py
pyGPs/Optimization/scg.py
pyGPs/Testing/unit_test_cov.py
pyGPs/Testing/unit_test_inf.py
pyGPs/Testing/unit_test_lik.py
pyGPs/Testing/unit_test_mean.py
pyGPs/Testing/unit_test_model.py
pyGPs/Testing/unit_test_opt.py
pyGPs/Validation/__init__.py
pyGPs/Validation/valid.py