Metadata-Version: 1.0
Name: pyGPs
Version: 1.3.3
Summary: Gaussian Processes for Regression and Classification
Home-page: https://github.com/marionmari/pyGPs
Author: ['Marion Neumann', 'Shan Huang', 'Daniel Marthaler', 'Kristian Kersting']
Author-email: ['marion.neumann@uni-bonn.de.com', 'shan.huang@iais.fraunhofer.de', 'dan.marthaler@gmail.com', 'kristian.kersting@cs.tu-dortmund.de']
License: COPYRIGHT.txt
Platform: UNKNOWN
